setup.py
OpenDPM/__init__.py
OpenDPM.egg-info/PKG-INFO
OpenDPM.egg-info/SOURCES.txt
OpenDPM.egg-info/dependency_links.txt
OpenDPM.egg-info/not-zip-safe
OpenDPM.egg-info/top_level.txt