Metadata-Version: 1.0
Name: OpenDPM
Version: 3
Summary: Open source Discrete Particles Modeling package
Home-page: https://github.com/314arham/OpenDPM
Author: 3.14arham
Author-email: prmbas@gmail.com
License: GPL-3.0
Platform: UNKNOWN
